odoo/addons/mgmtsystem_nonconformity_hazard/README.rst
odoo/addons/mgmtsystem_nonconformity_hazard/__init__.py
odoo/addons/mgmtsystem_nonconformity_hazard/__manifest__.py
odoo/addons/mgmtsystem_nonconformity_hazard/i18n/it.po
odoo/addons/mgmtsystem_nonconformity_hazard/i18n/mgmtsystem_nonconformity_hazard.pot
odoo/addons/mgmtsystem_nonconformity_hazard/models/__init__.py
odoo/addons/mgmtsystem_nonconformity_hazard/models/mgmtsystem_hazard.py
odoo/addons/mgmtsystem_nonconformity_hazard/models/mgmtsystem_nonconformity.py
odoo/addons/mgmtsystem_nonconformity_hazard/readme/CONTRIBUTORS.md
odoo/addons/mgmtsystem_nonconformity_hazard/readme/DESCRIPTION.md
odoo/addons/mgmtsystem_nonconformity_hazard/readme/USAGE.md
odoo/addons/mgmtsystem_nonconformity_hazard/static/description/icon.png
odoo/addons/mgmtsystem_nonconformity_hazard/static/description/index.html
odoo/addons/mgmtsystem_nonconformity_hazard/views/mgmtsystem_hazard.xml
odoo/addons/mgmtsystem_nonconformity_hazard/views/mgmtsystem_nonconformity.xml
odoo_addon_mgmtsystem_nonconformity_hazard-18.0.1.0.0.2.dist-info/METADATA
odoo_addon_mgmtsystem_nonconformity_hazard-18.0.1.0.0.2.dist-info/WHEEL
odoo_addon_mgmtsystem_nonconformity_hazard-18.0.1.0.0.2.dist-info/top_level.txt
odoo_addon_mgmtsystem_nonconformity_hazard-18.0.1.0.0.2.dist-info/RECORD
